ExcelBoot/__init__.py
ExcelBoot/boot.py
ExcelBoot/color2rgb.py
ExcelBoot/db.py
ExcelBoot/df_col_mapper.py
ExcelBoot/plt_ext.py
ExcelBoot/styleable_wrapper.py
ExcelBoot-1.0.1.dist-info/METADATA
ExcelBoot-1.0.1.dist-info/WHEEL
ExcelBoot-1.0.1.dist-info/entry_points.txt
ExcelBoot-1.0.1.dist-info/top_level.txt
ExcelBoot-1.0.1.dist-info/RECORD
