Metadata-Version: 2.1
Name: ExcelBoot
Version: 1.0.1
Summary: ExcelBoot: make an easy way (yaml) to auto generate excel
Home-page: https://github.com/shigebeyond/ExcelBoot
Author: shigebeyond
Author-email: 772910474@qq.com
License: BSD
Classifier: Development Status :: 5 - Production/Stable
Classifier: Topic :: Software Development :: Libraries :: Python Modules
Classifier: Operating System :: POSIX :: Linux
Classifier: Operating System :: MacOS :: MacOS X
Classifier: Operating System :: Microsoft :: Windows
Classifier: Programming Language :: Python
Classifier: Programming Language :: Python :: 3.7
Classifier: Programming Language :: Python :: 3.8
Classifier: Programming Language :: Python :: 3.9
Requires-Python: >=3.6
Requires-Dist: PyYAML (==6.0)
Requires-Dist: jsonpath (==0.82)
Requires-Dist: lxml (==4.3.2)
Requires-Dist: mysql-connector (==2.2.9)
Requires-Dist: pandas (==1.1.5)
Requires-Dist: SQLAlchemy (==1.4.23)
Requires-Dist: pyutilb (>=1.0.5)
Requires-Dist: openpyxl (==3.0.7)
